dashai_mlp_model_plugin/__init__.py
dashai_mlp_model_plugin/dataloader_class_template.py
dashai_mlp_model_plugin/metric_class_template.py
dashai_mlp_model_plugin/model_class_template.py
dashai_mlp_model_plugin/task_class_template.py
dashai_mlp_model_plugin-0.0.1.dist-info/METADATA
dashai_mlp_model_plugin-0.0.1.dist-info/WHEEL
dashai_mlp_model_plugin-0.0.1.dist-info/entry_points.txt
dashai_mlp_model_plugin-0.0.1.dist-info/RECORD
