Metadata-Version: 2.3
Name: dashai_mlp_model_plugin
Version: 0.0.1
Summary: DashAI Plugin description
Author: francisca
Author-email: francisca.cona@ug.uchile.cl
Keywords: DashAI,Model
Requires-Python: >=3.8
